qymeta/__init__.py
qymeta/qy/__init__.py
qymeta/qy/qy_nft.py
qymeta/qy_nft/__init__.py
qymeta/qy_nft/qy.py
qymeta_qy-0.0.1.dist-info/METADATA
qymeta_qy-0.0.1.dist-info/WHEEL
qymeta_qy-0.0.1.dist-info/top_level.txt
qymeta_qy-0.0.1.dist-info/RECORD
